plink_pipelines/__init__.py
plink_pipelines/make_dataset.py
plink_pipelines/validation_functions.py
plink_pipelines-0.8.3.dist-info/WHEEL
plink_pipelines-0.8.3.dist-info/entry_points.txt
plink_pipelines-0.8.3.dist-info/METADATA
plink_pipelines-0.8.3.dist-info/RECORD
